stripe_fees/__init__.py
stripe_fees/__main__.py
stripe_fees-0.0.2.dist-info/METADATA
stripe_fees-0.0.2.dist-info/WHEEL
stripe_fees-0.0.2.dist-info/licenses/LICENSE
stripe_fees-0.0.2.dist-info/RECORD
