Metadata-Version: 2.3
Name: stripe-fees
Version: 0.0.2
Summary: Python utility for calculating Stripe fees
Project-URL: homepage, https://github.com/Pavel-Sushko/stripe-fees
Project-URL: issues, https://github.com/Pavel-Sushko/stripe-fees/issues
Author-email: Pavel Sushko <github@psushko.com>
License: MIT License
License-File: LICENSE
Keywords: calculator,fees,stripe
Classifier: Development Status :: 5 - Production/Stable
Classifier: Environment :: Console
Classifier: Intended Audience :: Developers
Classifier: License :: OSI Approved :: MIT License
Classifier: Operating System :: MacOS :: MacOS X
Classifier: Operating System :: Microsoft :: Windows
Classifier: Operating System :: POSIX :: Linux
Classifier: Programming Language :: Python :: 3
Classifier: Programming Language :: Python :: 3.7
Classifier: Programming Language :: Python :: 3.8
Classifier: Programming Language :: Python :: 3.9
Classifier: Programming Language :: Python :: 3.10
Classifier: Programming Language :: Python :: 3.11
Classifier: Programming Language :: Python :: 3.12
Requires-Python: >=3.7
